{"pad\u00e1k": "der Fallschirm", "udr\u017eet, zastavit": "halten", "kost": "der Knochen", "schod": "die Treppe",
 "neuv\u011b\u0159iteln\u00fd": "unglaublich", "vodop\u00e1d": "der Wasserfall", "chlapci a d\u011bv\u010data": "Jungs und Madels",
  "dos\u00e1hnout, doc\u00edlit": "erzielen", "b\u011b\u017eec": "der Laufer", "z\u00e1pas": "das Match", "mistrovstv\u00ed": "die Meisterschaft",
   "obec": "der Ort", "bod": "der Punkt", "st\u0159elit": "schiessen", "dar, p\u0159\u00edsp\u011bvek": "die Spende", "br\u00e1na, gol": "das Tor",
    "prohr\u00e1t": "verlieren", "Dal gol.": "Er hat ein Tor erzielt."}